{
	"class" : {
		"consume1" : "MartinMcClure 9/13/2012 17:09",
		"echo1" : "MartinMcClure 9/13/2012 17:07",
		"fortyTwo" : "MartinMcClure 9/13/2012 17:05",
		"isB" : "MartinMcClure 9/17/2012 10:18",
		"print7" : "MartinMcClure 9/13/2012 17:03",
		"printH" : "MartinMcClure 9/13/2012 17:01",
		"threePlusFour" : "MartinMcClure 9/13/2012 16:58" },
	"instance" : {
		"compile:andRun:stdin:" : "tfel 9/6/2012 16:28",
		"compile:andWriteTo:" : "MartinMcClure 9/13/2012 15:57:48.636",
		"compileAndRun:" : "tfel 9/6/2012 16:27",
		"compileAndRun:stdin:" : "tfel 9/6/2012 16:25",
		"compileAndRun:withInput:expectingOutput:" : "MartinMcClure 9/17/2012 10:38",
		"execute:withStdin:" : "tfel 9/12/2012 16:34",
		"tearDown" : "tfel 9/6/2012 16:04",
		"testConsume1" : "MartinMcClure 9/13/2012 17:10",
		"testEcho1" : "MartinMcClure 9/17/2012 10:46",
		"testFortyTwo" : "MartinMcClure 9/13/2012 17:05",
		"testIsB" : "MartinMcClure 9/17/2012 10:48",
		"testPrint7" : "MartinMcClure 9/17/2012 10:44",
		"testPrintH" : "MartinMcClure 9/17/2012 10:45",
		"testThreePlusFour" : "MartinMcClure 9/13/2012 17:02",
		"waitForProcess:" : "tfel 9/12/2012 16:34" } }
